delphix/__init__.py
delphix/api/__init__.py
delphix/api/gateway/__init__.py
delphix/api/gateway/api_client.py
delphix/api/gateway/configuration.py
delphix/api/gateway/exceptions.py
delphix/api/gateway/model_utils.py
delphix/api/gateway/rest.py
delphix/api/gateway/api/__init__.py
delphix/api/gateway/api/accounts_api.py
delphix/api/gateway/api/ai_generate_api.py
delphix/api/gateway/api/ai_management_api.py
delphix/api/gateway/api/algorithms_api.py
delphix/api/gateway/api/authorization_api.py
delphix/api/gateway/api/bookmarks_api.py
delphix/api/gateway/api/cdb_d_sources_api.py
delphix/api/gateway/api/cdbs_api.py
delphix/api/gateway/api/classifiers_api.py
delphix/api/gateway/api/compliance_job_collections_api.py
delphix/api/gateway/api/compliance_jobs_api.py
delphix/api/gateway/api/connectivity_api.py
delphix/api/gateway/api/connectors_api.py
delphix/api/gateway/api/d_sources_api.py
delphix/api/gateway/api/data_classes_api.py
delphix/api/gateway/api/data_connections_api.py
delphix/api/gateway/api/data_layouts_api.py
delphix/api/gateway/api/database_templates_api.py
delphix/api/gateway/api/discovery_expressions_api.py
delphix/api/gateway/api/discovery_policies_api.py
delphix/api/gateway/api/environments_api.py
delphix/api/gateway/api/executions_api.py
delphix/api/gateway/api/file_mapping_api.py
delphix/api/gateway/api/groups_api.py
delphix/api/gateway/api/held_space_api.py
delphix/api/gateway/api/hook_templates_api.py
delphix/api/gateway/api/hyperscale_instance_api.py
delphix/api/gateway/api/hyperscale_objects_api.py
delphix/api/gateway/api/job_collection_executions_api.py
delphix/api/gateway/api/jobs_api.py
delphix/api/gateway/api/kerberos_config_api.py
delphix/api/gateway/api/license_api.py
delphix/api/gateway/api/login_api.py
delphix/api/gateway/api/management_api.py
delphix/api/gateway/api/masking_environments_api.py
delphix/api/gateway/api/masking_files_api.py
delphix/api/gateway/api/masking_jobs_api.py
delphix/api/gateway/api/namespace_api.py
delphix_dct_api-2026.1.0.dist-info/METADATA
delphix_dct_api-2026.1.0.dist-info/WHEEL
delphix_dct_api-2026.1.0.dist-info/top_level.txt
delphix_dct_api-2026.1.0.dist-info/RECORD
