Metadata-Version: 2.4
Name: delphix-dct-api
Version: 2026.1.0
Summary: Delphix DCT API
Home-page: 
Author: Delphix Support
Author-email: support@delphix.com
Keywords: OpenAPI,OpenAPI-Generator,Delphix DCT API
Requires-Python: >=3.6
Requires-Dist: urllib3>=1.25.3
Requires-Dist: python-dateutil
Dynamic: author
Dynamic: author-email
Dynamic: description
Dynamic: keywords
Dynamic: requires-dist
Dynamic: requires-python
Dynamic: summary
